google_generativeai-0.1.0rc3-py3.10-nspkg.pth
google/generativeai/__init__.py
google/generativeai/client.py
google/generativeai/discuss.py
google/generativeai/docstring_utils.py
google/generativeai/models.py
google/generativeai/text.py
google/generativeai/version.py
google/generativeai/notebook/__init__.py
google/generativeai/notebook/argument_parser.py
google/generativeai/notebook/argument_parser_test.py
google/generativeai/notebook/cmd_line_parser.py
google/generativeai/notebook/cmd_line_parser_test.py
google/generativeai/notebook/command.py
google/generativeai/notebook/command_utils.py
google/generativeai/notebook/compare_cmd.py
google/generativeai/notebook/compile_cmd.py
google/generativeai/notebook/eval_cmd.py
google/generativeai/notebook/flag_def.py
google/generativeai/notebook/flag_def_test.py
google/generativeai/notebook/gspread_client.py
google/generativeai/notebook/html_utils.py
google/generativeai/notebook/html_utils_test.py
google/generativeai/notebook/input_utils.py
google/generativeai/notebook/input_utils_test.py
google/generativeai/notebook/ipython_env.py
google/generativeai/notebook/ipython_env_impl.py
google/generativeai/notebook/magics.py
google/generativeai/notebook/magics_engine.py
google/generativeai/notebook/magics_engine_test.py
google/generativeai/notebook/model_registry.py
google/generativeai/notebook/model_registry_test.py
google/generativeai/notebook/output_utils.py
google/generativeai/notebook/parsed_args_lib.py
google/generativeai/notebook/post_process_utils.py
google/generativeai/notebook/post_process_utils_test.py
google/generativeai/notebook/post_process_utils_test_helper.py
google/generativeai/notebook/py_utils.py
google/generativeai/notebook/py_utils_test.py
google/generativeai/notebook/run_cmd.py
google/generativeai/notebook/sheets_id.py
google/generativeai/notebook/sheets_id_test.py
google/generativeai/notebook/sheets_sanitize_url.py
google/generativeai/notebook/sheets_sanitize_url_test.py
google_generativeai-0.1.0rc3.dist-info/LICENSE
google_generativeai-0.1.0rc3.dist-info/METADATA
google_generativeai-0.1.0rc3.dist-info/WHEEL
google_generativeai-0.1.0rc3.dist-info/namespace_packages.txt
google_generativeai-0.1.0rc3.dist-info/top_level.txt
google_generativeai-0.1.0rc3.dist-info/RECORD
